{"chunk_definitions":[{"row":18,"row_count":1,"visible":true,"expansion_state":0,"options":{"engine":"r","label":"loading libraries","include":false,"message":false},"document_id":"D8DD5288","chunk_id":"c4z8oo7apz1ty","chunk_label":"loading libraries"},{"row":81,"row_count":1,"visible":true,"expansion_state":0,"options":{"engine":"r","label":"unnamed-chunk-8"},"document_id":"D8DD5288","chunk_id":"cmybbuux63p23","chunk_label":"unnamed-chunk-2"},{"row":98,"row_count":1,"visible":true,"expansion_state":0,"options":{"engine":"r","label":"unnamed-chunk-1"},"document_id":"D8DD5288","chunk_id":"cxtpsxpqbc4wo","chunk_label":"unnamed-chunk-3"},{"row":111,"row_count":1,"visible":true,"expansion_state":0,"options":{"engine":"r","label":"unnamed-chunk-7"},"document_id":"D8DD5288","chunk_id":"c1th2ciohtncl","chunk_label":"unnamed-chunk-4"}],"doc_write_time":1689935700,"chunk_rendered_width":622}